{
    "states": [
        "0.0",
        "1.1",
        "0.2",
        "1.2",
        "1.0"
    ],
    "alphabet": [
        "c",
        "a",
        "b"
    ],
    "transitions": [
        {
            "from": "0.0",
            "with": "c",
            "to": "0.0"
        },
        {
            "from": "0.0",
            "with": "a",
            "to": "1.1"
        },
        {
            "from": "0.0",
            "with": "b",
            "to": "0.0"
        },
        {
            "from": "1.1",
            "with": "c",
            "to": "1.1"
        },
        {
            "from": "1.1",
            "with": "a",
            "to": "1.1"
        },
        {
            "from": "1.1",
            "with": "b",
            "to": "0.2"
        },
        {
            "from": "0.2",
            "with": "c",
            "to": "0.0"
        },
        {
            "from": "0.2",
            "with": "a",
            "to": "1.2"
        },
        {
            "from": "0.2",
            "with": "b",
            "to": "0.2"
        },
        {
            "from": "1.2",
            "with": "c",
            "to": "1.0"
        },
        {
            "from": "1.2",
            "with": "a",
            "to": "1.2"
        },
        {
            "from": "1.2",
            "with": "b",
            "to": "0.2"
        },
        {
            "from": "1.0",
            "with": "c",
            "to": "1.0"
        },
        {
            "from": "1.0",
            "with": "a",
            "to": "1.1"
        },
        {
            "from": "1.0",
            "with": "b",
            "to": "0.0"
        }
    ],
    "initial_state": "0.0",
    "accepting_states": [
        "1.2"
    ]
}